new_rtorrent_python-1.0.1a0.dist-info/DESCRIPTION.rst
new_rtorrent_python-1.0.1a0.dist-info/METADATA
new_rtorrent_python-1.0.1a0.dist-info/RECORD
new_rtorrent_python-1.0.1a0.dist-info/WHEEL
new_rtorrent_python-1.0.1a0.dist-info/metadata.json
new_rtorrent_python-1.0.1a0.dist-info/top_level.txt
rtorrent/__init__.py
rtorrent/common.py
rtorrent/context.py
rtorrent/err.py
rtorrent/file.py
rtorrent/group.py
rtorrent/peer.py
rtorrent/torrent.py
rtorrent/tracker.py
rtorrent/lib/torrentparser.py
rtorrent/lib/xmlrpc/basic_auth.py
rtorrent/lib/xmlrpc/requests_transport.py
rtorrent/lib/xmlrpc/scgi.py
rtorrent/rpc/__init__.py
rtorrent/rpc/call.py
rtorrent/rpc/caller.py
rtorrent/rpc/method.py
rtorrent/rpc/processors.py
rtorrent/rpc/result.py
